tkdevin/__init__.py
tkdevin/gradient.py
tkdevin/mark.py
tkdevin/move.py
tkdevin/selectcanvas.py
tkdevin/tooltip.py
tkdevin/dctk/__init__.py
tkdevin/dtk/__init__.py
tkdevin-0.0.3.dist-info/METADATA
tkdevin-0.0.3.dist-info/WHEEL
tkdevin-0.0.3.dist-info/top_level.txt
tkdevin-0.0.3.dist-info/RECORD
