Metadata-Version: 2.1
Name: tkdevin
Version: 0.0.3
Summary: tkinter extension library
Author: XiangQinxi
Author-email: XiangQinxi@outlook.com
Classifier: Programming Language :: Python :: 3
Classifier: License :: OSI Approved :: MIT License
Classifier: Operating System :: OS Independent
Requires-Python: >=3
